setup.cfg
setup.py
plugs/.DS_Store
plugs/__init__.py
plugs/_project
plugs/wiki.zip
plugs.egg-info/PKG-INFO
plugs.egg-info/SOURCES.txt
plugs.egg-info/dependency_links.txt
plugs.egg-info/entry_points.txt
plugs.egg-info/not-zip-safe
plugs.egg-info/top_level.txt
plugs/admin/__init__.py
plugs/admin/conf.py
plugs/admin/config.ini
plugs/admin/info.ini
plugs/admin/settings.ini
plugs/admin/views.py
plugs/admin/static/readme.txt
plugs/admin/static/admin/admin.css
plugs/admin/templates/admin_layout.html
plugs/admin/templates/readme.txt
plugs/admin/templates/AdminView/index.html
plugs/audit/__init__.py
plugs/audit/conf.py
plugs/audit/info.ini
plugs/audit/models.py
plugs/audit/settings.ini
plugs/audit/views.py
plugs/audit/static/readme.txt
plugs/audit/templates/audit_recent.html
plugs/audit/templates/readme.txt
plugs/develop/__init__.py
plugs/develop/config.ini
plugs/develop/forms.py
plugs/develop/info.ini
plugs/develop/menu.py
plugs/develop/settings.ini
plugs/develop/views.py
plugs/develop/static/css/develop.css
plugs/develop/static/css/layout_shiny_buttons.css
plugs/develop/static/css/layout_sliding_door.css
plugs/develop/static/css/layout_vertical_listnav.css
plugs/develop/static/css/tabs.css
plugs/develop/static/css/patches/patch_shiny_buttons.css
plugs/develop/static/css/patches/patch_sliding_door.css
plugs/develop/static/css/patches/patch_vertical_listnav.css
plugs/develop/static/css/screen/basemod.css
plugs/develop/static/css/screen/basemod_slidingdoor.css
plugs/develop/static/css/screen/content.css
plugs/develop/static/images/bg_blue.png
plugs/develop/static/images/bg_header.png
plugs/develop/static/js/Fx.Slide.js
plugs/develop/static/js/clientcide-tabswap.js
plugs/develop/templates/develop_app_generic.html
plugs/develop/templates/develop_app_show.html
plugs/develop/templates/develop_appsinfo.html
plugs/develop/templates/develop_build.html
plugs/develop/templates/develop_globals.html
plugs/develop/templates/develop_index.html
plugs/develop/templates/develop_layout.html
plugs/develop/templates/develop_urls.html
plugs/forums/__init__.py
plugs/forums/conf.py
plugs/forums/config.ini
plugs/forums/forms.py
plugs/forums/info.ini
