Metadata-Version: 1.1
Name: plugs
Version: 0.2
Summary: Apps collection for uliweb
Home-page: https://github.com/limodou/plugs
Author: limodou
Author-email: limodou@gmail.com
License: BSD
Keywords: wsgi web framework
Platform: any
Classifier: Development Status :: 2 - Pre-Alpha
Classifier: Intended Audience :: Developers
Classifier: License :: OSI Approved :: BSD License
Classifier: Topic :: Internet :: WWW/HTTP :: WSGI
Classifier: Programming Language :: Python
Classifier: Operating System :: OS Independent
Classifier: Programming Language :: Python :: 2.6
Classifier: Programming Language :: Python :: 2.7
